README.md
setup.cfg
setup.py
django_saferpay.egg-info/PKG-INFO
django_saferpay.egg-info/SOURCES.txt
django_saferpay.egg-info/dependency_links.txt
django_saferpay.egg-info/requires.txt
django_saferpay.egg-info/top_level.txt
saferpay/__init__.py
saferpay/admin.py
saferpay/execptions.py
saferpay/gateway.py
saferpay/models.py
saferpay/urls.py
saferpay/views.py
saferpay/migrations/0001_initial.py
saferpay/migrations/0002_saferpaytransaction_language_code.py
saferpay/migrations/0003_saferpayresponse_status_code.py
saferpay/migrations/0004_auto_20180815_1251.py
saferpay/migrations/0005_saferpaytransaction_has_notify.py
saferpay/migrations/0006_saferpaytransaction_notify_token.py
saferpay/migrations/0007_auto_20180911_2207.py
saferpay/migrations/__init__.py