Metadata-Version: 2.1
Name: django-saferpay
Version: 0.1.1
Summary: Saferpay payment integration for django.
Home-page: https://github.com/taywa/django-saferpay
Author: Yves Serrano
Author-email: ys@taywa.ch
License: MIT
Keywords: saferpay,payment
Platform: UNKNOWN
Classifier: Development Status :: 4 - Beta
Classifier: Environment :: Web Environment
Classifier: Intended Audience :: Developers
Classifier: License :: OSI Approved :: MIT License
Classifier: Operating System :: OS Independent
Classifier: Topic :: Software Development :: Libraries :: Python Modules
Classifier: Programming Language :: Python :: 3
Classifier: Programming Language :: Python :: 3.6
Classifier: Programming Language :: Python :: 3.7
Classifier: Framework :: Django
Classifier: Framework :: Django :: 1.11
Classifier: Framework :: Django :: 2.0
Classifier: Framework :: Django :: 2.1
